context_cite/__init__.py
context_cite/context_citer.py
context_cite/context_partitioner.py
context_cite/solver.py
context_cite/utils.py
context_cite-0.0.4.dist-info/LICENSE
context_cite-0.0.4.dist-info/METADATA
context_cite-0.0.4.dist-info/WHEEL
context_cite-0.0.4.dist-info/top_level.txt
context_cite-0.0.4.dist-info/RECORD
