Metadata-Version: 2.1
Name: context-cite
Version: 0.0.4
Summary: Attribute (or cite) statements generated by LLMs back to in-context information.
Author-email: MadryLab <contextcite@mit.edu>
Project-URL: Homepage, https://github.com/MadryLab/context-cite
Project-URL: Issues, https://github.com/MadryLab/context-cite/issues
Classifier: Programming Language :: Python :: 3
Classifier: License :: OSI Approved :: MIT License
Classifier: Operating System :: OS Independent
Requires-Python: >=3.8
License-File: LICENSE
Requires-Dist: numpy
Requires-Dist: torch
Requires-Dist: transformers
Requires-Dist: datasets
Requires-Dist: pandas
Requires-Dist: nltk >=3.8.2
Requires-Dist: spacy
Requires-Dist: scikit-learn
Requires-Dist: tqdm
Provides-Extra: test
Requires-Dist: pytest ; extra == 'test'
